pads_gpt_assistant/__init__.py
pads_gpt_assistant/coding_gpt.py
pads_gpt_assistant/config.py
pads_gpt_assistant-0.0.1.dev0.dist-info/LICENSE
pads_gpt_assistant-0.0.1.dev0.dist-info/METADATA
pads_gpt_assistant-0.0.1.dev0.dist-info/WHEEL
pads_gpt_assistant-0.0.1.dev0.dist-info/top_level.txt
pads_gpt_assistant-0.0.1.dev0.dist-info/RECORD
