Metadata-Version: 2.1
Name: pads-gpt-assistant
Version: 0.0.1.dev0
Summary: Coding Assistance using ChatGPT from OpenAI
Home-page: https://github.com/leeparkuky/pads-coding-assistant
Author: Lee Park
Author-email: <lee.park@uky.edu>
License: Apache-2.0
Keywords: ChatGPT,Kentucky,Statistics,PADS,Coding Assistant
Classifier: Development Status :: 1 - Planning
Classifier: Intended Audience :: Developers
Classifier: Programming Language :: Python :: 3
Classifier: Operating System :: Unix
Classifier: Operating System :: MacOS :: MacOS X
Classifier: Operating System :: Microsoft :: Windows
Requires-Python: >=3.7.1
License-File: LICENSE
Requires-Dist: openai
Requires-Dist: pandas
